mortal_sqlglot/__init__.py
mortal_sqlglot/sqlglot_main.cp310-win_amd64.pyd
mortal_sqlglot/test.cp310-win_amd64.pyd
mortal_sqlglot-4.1.0.dist-info/METADATA
mortal_sqlglot-4.1.0.dist-info/WHEEL
mortal_sqlglot-4.1.0.dist-info/top_level.txt
mortal_sqlglot-4.1.0.dist-info/RECORD
