Metadata-Version: 2.4
Name: mortal_sqlglot
Version: 4.1.0
Summary: mortal工具集::sqlglot
Home-page: https://www.example.com
Author: Mortal
Author-email: mortal9098@163.com
License: MIT
Classifier: Development Status :: 4 - Beta
Classifier: Programming Language :: Python :: 3
Classifier: Programming Language :: Python :: 3.10
Classifier: Operating System :: Microsoft :: Windows
Classifier: Intended Audience :: Developers
Requires-Python: >=3.7
Requires-Dist: mortal-bases
Requires-Dist: mortal-var
Requires-Dist: mortal-crypt
Requires-Dist: sqlglot
Requires-Dist: prettytable
Dynamic: author
Dynamic: author-email
Dynamic: classifier
Dynamic: description
Dynamic: description-content-type
Dynamic: home-page
Dynamic: license
Dynamic: requires-dist
Dynamic: requires-python
Dynamic: summary
